{
  "types": {
    "NpcId": "int;id",
    "MenuName": "local_string;[NpcId][Order]",
    "ShowRequirement": "enum<RequirementType>",
    "ShowRequirementValues": "list<int>",
    "HideRequirement": "enum<RequirementType>",
    "HideRequirementValues": "list<int>",
    "Order": "int",
    "ShowBubble": "bool",
    "FunctionType": "enum<NpcMenuFunctionType>",
    "FunctionValue": "int;id"
  },
  "rows": [
    [
      1000009,
      "MapNpcData.MapNpcMenu.1000009.1",
      "AlwaysTrue",
      "",
      "AlwaysFalse",
      "",
      1,
      0,
      "PlayCutscene",
      1000010
    ],
    [
      1000009,
      "MapNpcData.MapNpcMenu.1000009.2",
      "AlwaysTrue",
      "",
      "AlwaysFalse",
      "",
      2,
      1,
      "PlaySlimeMinigame",
      0
    ]
  ]
}